beewa/__init__.py
beewa/beewa.py
beewa/cli.py
beewa/hive.py
beewa-0.4.5.dist-info/LICENSE
beewa-0.4.5.dist-info/METADATA
beewa-0.4.5.dist-info/WHEEL
beewa-0.4.5.dist-info/entry_points.txt
beewa-0.4.5.dist-info/top_level.txt
beewa-0.4.5.dist-info/RECORD
