Metadata-Version: 2.1
Name: beewa
Version: 0.4.5
Summary: beewa makes controlling your hivehome.com powered system easy!
Home-page: https://github.com/matthewgall/beewa
Author: Matthew Gall
Author-email: git@matthewgall.com
License: MIT
Platform: linux
Classifier: Development Status :: 4 - Beta
Classifier: Environment :: Console
Classifier: Intended Audience :: Developers
Classifier: License :: OSI Approved :: MIT License
Classifier: Programming Language :: Python :: 2
Classifier: Programming Language :: Python :: 3
Requires-Dist: requests
